[dotenv@17.3.1] injecting env (7) from .env -- tip: ≡ƒöÉ encrypt with Dotenvx: https://dotenvx.com
[dotenv@17.3.1] injecting env (0) from .env -- tip: ΓÜÖ∩╕Å  load multiple .env files with { path: ['.env.local', '.env'] }
[
  {
    "table_name": "users"
  },
  {
    "table_name": "daily_status"
  },
  {
    "table_name": "user_interests"
  },
  {
    "table_name": "interests"
  },
  {
    "table_name": "activities"
  },
  {
    "table_name": "activity_images"
  },
  {
    "table_name": "activity_tags"
  },
  {
    "table_name": "activity_requests"
  },
  {
    "table_name": "follows"
  },
  {
    "table_name": "match_sessions"
  },
  {
    "table_name": "conversations"
  },
  {
    "table_name": "conversation_members"
  },
  {
    "table_name": "messages"
  },
  {
    "table_name": "notifications"
  },
  {
    "table_name": "reports"
  },
  {
    "table_name": "reputation_logs"
  },
  {
    "table_name": "banned_keywords"
  },
  {
    "table_name": "system_config"
  },
  {
    "table_name": "post_reactions"
  },
  {
    "table_name": "post_comments"
  },
  {
    "table_name": "post_shares"
  }
]
